sg_hello_pypi/__init__.py
sg_hello_pypi-0.2.1.dist-info/LICENSE
sg_hello_pypi-0.2.1.dist-info/METADATA
sg_hello_pypi-0.2.1.dist-info/WHEEL
sg_hello_pypi-0.2.1.dist-info/RECORD
