Metadata-Version: 2.1
Name: sg-hello-pypi
Version: 0.2.1
Summary: Demo package to publish
License: MIT
Author: Soof Golan
Author-email: soofgolan@gmail.com
Requires-Python: >=3.8,<4.0
Classifier: License :: OSI Approved :: MIT License
Classifier: Programming Language :: Python :: 3
Classifier: Programming Language :: Python :: 3.8
Classifier: Programming Language :: Python :: 3.9
Classifier: Programming Language :: Python :: 3.10
Classifier: Programming Language :: Python :: 3.11
Requires-Dist: typing-extensions (>=4.5.0,<5.0.0)
